scriptcheck/__init__.py
scriptcheck/scriptcheck.py
scriptcheck-0.0.1.dist-info/METADATA
scriptcheck-0.0.1.dist-info/WHEEL
scriptcheck-0.0.1.dist-info/entry_points.txt
scriptcheck-0.0.1.dist-info/licenses/LICENSE.txt
scriptcheck-0.0.1.dist-info/RECORD
