Metadata-Version: 2.1
Name: scriptcheck
Version: 0.0.1
Summary: Print a list of scripts from your Python Scripts folder for when you're like me and can't remember what you've installed or what a tool is called.
Project-URL: Homepage, https://github.com/matt-manes/scriptcheck
Project-URL: Documentation, https://github.com/matt-manes/scriptcheck/tree/main/docs
Project-URL: Source code, https://github.com/matt-manes/scriptcheck/tree/main/src/scriptcheck
Author-email: Matt Manes <mattmanes@pm.me>
License-File: LICENSE.txt
Classifier: License :: OSI Approved :: MIT License
Classifier: Operating System :: OS Independent
Classifier: Programming Language :: Python :: 3
Requires-Python: >=3.10
Requires-Dist: pathier
Requires-Dist: pytest
Requires-Dist: younotyou
